pycirk/__init__.py
pycirk/cli.py
pycirk/fundamental_operations.py
pycirk/labels.py
pycirk/make_scenarios.py
pycirk/make_secondary_flows.py
pycirk/organize_io.py
pycirk/positions.py
pycirk/pycirk.py
pycirk/pycirk_settings.py
pycirk/results.py
pycirk/save_utils.py
pycirk/scenarios.xlsx
pycirk/transformation_methods.py
pycirk/data/README.txt
pycirk/labels/charact_emissions.csv
pycirk/labels/charact_factor_inputs.csv
pycirk/labels/charact_materials.csv
pycirk/labels/charact_resources.csv
pycirk/labels/emissions.csv
pycirk/labels/factor_inputs.csv
pycirk/labels/final_demand.csv
pycirk/labels/industry.csv
pycirk/labels/materials.csv
pycirk/labels/products.csv
pycirk/labels/resources.csv
pycirk-2.0.dist-info/AUTHORS.rst
pycirk-2.0.dist-info/LICENSE
pycirk-2.0.dist-info/METADATA
pycirk-2.0.dist-info/WHEEL
pycirk-2.0.dist-info/entry_points.txt
pycirk-2.0.dist-info/top_level.txt
pycirk-2.0.dist-info/RECORD
