Metadata-Version: 2.1
Name: pycirk
Version: 2.0
Summary: A software to model Circular Economy policy andtechnological interventions in Environmentally Extended Input-Output Analysis (EXIOBASE V3.3)
Home-page: https://bitbucket.org/CML-IE/pycirk/src/master/
Author: Franco Donati
Author-email: f.donati@cml.leidenuniv.nl
License: GNU General Public License v3
Keywords: pycirk
Platform: UNKNOWN
Classifier: Development Status :: 4 - Beta
Classifier: Intended Audience :: Developers
Classifier: License :: OSI Approved :: GNU General Public License v3 (GPLv3)
Classifier: Natural Language :: English
Classifier: Programming Language :: Python :: 3.5
Classifier: Programming Language :: Python :: 3.6
Classifier: Programming Language :: Python :: 3.7
Classifier: Programming Language :: Python :: 3.8
Classifier: Programming Language :: Python :: 3 :: Only
Requires-Dist: appdirs (==1.4.3)
Requires-Dist: munch (==2.5.0)
Requires-Dist: openpyxl (==3.0.7)
Requires-Dist: pandas (==1.2.4)
